{
  "name": "ubuntu-22.04",
  "version": "202404.26.0",
  "arch": "aarch64",
  "build_timestamp": "20240426132914",
  "packer_command": "packer build -timestamp-ui -force -var cpus=4 -only=vmware-iso.vm -var-file=ubuntu-22.04-aarch64.pkrvars.hcl ../../packer_templates",
  "git_revision": "203544c7893b23b051da5694012ff6a9bf3ac0ea",
  "git_status": "dirty",
  "box_basename": "ubuntu-22.04",
  "template": "ubuntu-22.04-aarch64",
  "packer": "Packer v1.10.2",
  "providers": [
    {
      "name": "vmware_desktop",
      "version": "13.5.1",
      "file": "ubuntu-22.04-aarch64.vmware.box",
      "checksum_type": "sha256",
      "checksum": "ba630cce26801cb66b9f2cce794f17d24eb7ec5275bbdcdd8e6de2c17261b96e",
      "size": "935 MB",
      "build_time": 567,
      "build_cpus": "4"
    }
  ]
}